{
"instructions_readme": "1) Open Chrome, 2) go to chrome://tracing, 3) click Load, 4) navigate to this file.",

"traceEvents":[
{ "pid": 1, "tid": 1, "ph": "M", "name": "thread_name", "args": { "name": "" } },
{ "pid": 1, "tid": 1, "ts": 756.5, "dur": 15195838.4, "ph": "X", "name": "il2cpp.exe", "args": { "durationMS": 15195.8384, "detail": "" } },
{ "pid": 1, "tid": 1, "ts": 15947.7, "dur": 15180606.4, "ph": "X", "name": "ConvertAssemblies", "args": { "durationMS": 15180.6064, "detail": "" } },
{ "pid": 1, "tid": 1, "ts": 36911.2, "dur": 85580.8, "ph": "X", "name": "Collect assemblies to convert", "args": { "durationMS": 85.5808, "detail": "" } },
{ "pid": 1, "tid": 1, "ts": 122797.2, "dur": 33255, "ph": "X", "name": "RegisterCorlib", "args": { "durationMS": 33.255, "detail": "" } },
{ "pid": 1, "tid": 1, "ts": 156203.8, "dur": 43779.2, "ph": "X", "name": "PreProcessIL", "args": { "durationMS": 43.7792, "detail": "" } },
{ "pid": 1, "tid": 1, "ts": 156204.9, "dur": 7492.2, "ph": "X", "name": "Inject base types and finalizers into COM and Windows Runtime types", "args": { "durationMS": 7.4922, "detail": "" } },
{ "pid": 1, "tid": 1, "ts": 156384.8, "dur": 5869.3, "ph": "X", "name": "ModifyCOMAndWindowsRuntimeTypes in assembly", "args": { "durationMS": 5.8693, "detail": "mscorlib" } },
{ "pid": 1, "tid": 1, "ts": 163699, "dur": 36283.9, "ph": "X", "name": "ApplyDefaultMarshalAsAttribute", "args": { "durationMS": 36.2839, "detail": "" } },
{ "pid": 1, "tid": 1, "ts": 163844.7, "dur": 22492.9, "ph": "X", "name": "ApplyDefaultMarshalAsAttributeVisitor in assembly", "args": { "durationMS": 22.4929, "detail": "mscorlib" } },
{ "pid": 1, "tid": 1, "ts": 186450.6, "dur": 1862.4, "ph": "X", "name": "ApplyDefaultMarshalAsAttributeVisitor in assembly", "args": { "durationMS": 1.8624, "detail": "System" } },
{ "pid": 1, "tid": 1, "ts": 188502.3, "dur": 3463.8, "ph": "X", "name": "ApplyDefaultMarshalAsAttributeVisitor in assembly", "args": { "durationMS": 3.4638, "detail": "UnityEngine.CoreModule" } },
{ "pid": 1, "tid": 1, "ts": 193662.8, "dur": 1347.9, "ph": "X", "name": "ApplyDefaultMarshalAsAttributeVisitor in assembly", "args": { "durationMS": 1.3479, "detail": "UnityEngine.UI" } },
{ "pid": 1, "tid": 1, "ts": 195176.7, "dur": 4548.4, "ph": "X", "name": "ApplyDefaultMarshalAsAttributeVisitor in assembly", "args": { "durationMS": 4.5484, "detail": "Unity.TextMeshPro" } },
{ "pid": 1, "tid": 1, "ts": 200056.3, "dur": 5881.2, "ph": "X", "name": "WriteResources", "args": { "durationMS": 5.8812, "detail": "" } },
{ "pid": 1, "tid": 1, "ts": 206033.3, "dur": 20532, "ph": "X", "name": "CopyEtcFolder", "args": { "durationMS": 20.532, "detail": "" } },
{ "pid": 1, "tid": 1, "ts": 227151.3, "dur": 174160, "ph": "X", "name": "PreProcessStage", "args": { "durationMS": 174.16, "detail": "" } },
{ "pid": 1, "tid": 1, "ts": 401928.4, "dur": 1692.5, "ph": "X", "name": "Debugger Sequence Points", "args": { "durationMS": 1.6925, "detail": "" } },
{ "pid": 1, "tid": 1, "ts": 404922.4, "dur": 1008534.8, "ph": "X", "name": "Generics Collection", "args": { "durationMS": 1008.5348, "detail": "" } },
{ "pid": 1, "tid": 1, "ts": 404923.5, "dur": 986777.6, "ph": "X", "name": "GenericsCollector.Collect", "args": { "durationMS": 986.7776, "detail": "" } },
{ "pid": 1, "tid": 1, "ts": 405929.5, "dur": 18344.2, "ph": "X", "name": "GenericCodeFlowGraphCollector.Collect", "args": { "durationMS": 18.3442, "detail": "" } },
{ "pid": 1, "tid": 1, "ts": 405930.4, "dur": 17735.9, "ph": "X", "name": "GenericCodeFlowGraphCollector.GetTypesAndMethodsForAnalysis", "args": { "durationMS": 17.7359, "detail": "" } },
{ "pid": 1, "tid": 1, "ts": 1391708.3, "dur": 20792.5, "ph": "X", "name": "CollectGenericVirtualMethods.Collect", "args": { "durationMS": 20.7925, "detail": "" } },
{ "pid": 1, "tid": 1, "ts": 1412503.4, "dur": 588.8, "ph": "X", "name": "AddExtraTypes", "args": { "durationMS": 0.5888, "detail": "" } },
{ "pid": 1, "tid": 1, "ts": 1413458.6, "dur": 1103.5, "ph": "X", "name": "Add Windows Runtime type names", "args": { "durationMS": 1.1035, "detail": "" } },
{ "pid": 1, "tid": 1, "ts": 1415100.3, "dur": 7761088, "ph": "X", "name": "AllAssemblyConversion", "args": { "durationMS": 7761.088, "detail": "" } },
{ "pid": 1, "tid": 1, "ts": 1415584.7, "dur": 3445253.6, "ph": "X", "name": "Convert assembly non-generic methods", "args": { "durationMS": 3445.2536, "detail": "mscorlib" } },
{ "pid": 1, "tid": 1, "ts": 4860840.8, "dur": 3860.5, "ph": "X", "name": "Convert assembly non-generic methods", "args": { "durationMS": 3.8605, "detail": "System.Configuration" } },
{ "pid": 1, "tid": 1, "ts": 4864702.4, "dur": 11675.3, "ph": "X", "name": "Convert assembly non-generic methods", "args": { "durationMS": 11.6753, "detail": "Mono.Security" } },
{ "pid": 1, "tid": 1, "ts": 4876379.2, "dur": 11492.6, "ph": "X", "name": "Convert assembly non-generic methods", "args": { "durationMS": 11.4926, "detail": "System.Xml" } },
{ "pid": 1, "tid": 1, "ts": 4887872.8, "dur": 423322.4, "ph": "X", "name": "Convert assembly non-generic methods", "args": { "durationMS": 423.3224, "detail": "System" } },
{ "pid": 1, "tid": 1, "ts": 5311198, "dur": 1293.1, "ph": "X", "name": "Convert assembly non-generic methods", "args": { "durationMS": 1.2931, "detail": "System.Core" } },
{ "pid": 1, "tid": 1, "ts": 5312492.8, "dur": 16540.4, "ph": "X", "name": "Convert assembly non-generic methods", "args": { "durationMS": 16.5404, "detail": "UnityEngine.SharedInternalsModule" } },
{ "pid": 1, "tid": 1, "ts": 5329035.2, "dur": 543252.9, "ph": "X", "name": "Convert assembly non-generic methods", "args": { "durationMS": 543.2529, "detail": "UnityEngine.CoreModule" } },
{ "pid": 1, "tid": 1, "ts": 5872289.6, "dur": 781.6, "ph": "X", "name": "Convert assembly non-generic methods", "args": { "durationMS": 0.7816, "detail": "UnityEngine.GridModule" } },
{ "pid": 1, "tid": 1, "ts": 5873072.4, "dur": 14399.2, "ph": "X", "name": "Convert assembly non-generic methods", "args": { "durationMS": 14.3992, "detail": "UnityEngine.InputLegacyModule" } },
{ "pid": 1, "tid": 1, "ts": 5887473.2, "dur": 35850.1, "ph": "X", "name": "Convert assembly non-generic methods", "args": { "durationMS": 35.8501, "detail": "UnityEngine.Physics2DModule" } },
{ "pid": 1, "tid": 1, "ts": 5923324.8, "dur": 26454.7, "ph": "X", "name": "Convert assembly non-generic methods", "args": { "durationMS": 26.4547, "detail": "UnityEngine.PhysicsModule" } },
{ "pid": 1, "tid": 1, "ts": 5949781.2, "dur": 12915, "ph": "X", "name": "Convert assembly non-generic methods", "args": { "durationMS": 12.915, "detail": "UnityEngine.SubsystemsModule" } },
{ "pid": 1, "tid": 1, "ts": 5962698, "dur": 20513.9, "ph": "X", "name": "Convert assembly non-generic methods", "args": { "durationMS": 20.5139, "detail": "UnityEngine.TextRenderingModule" } },
{ "pid": 1, "tid": 1, "ts": 5983213.6, "dur": 28345.9, "ph": "X", "name": "Convert assembly non-generic methods", "args": { "durationMS": 28.3459, "detail": "UnityEngine.AnimationModule" } },
{ "pid": 1, "tid": 1, "ts": 6011561.2, "dur": 7015.2, "ph": "X", "name": "Convert assembly non-generic methods", "args": { "durationMS": 7.0152, "detail": "UnityEngine.AssetBundleModule" } },
{ "pid": 1, "tid": 1, "ts": 6018578, "dur": 12754.6, "ph": "X", "name": "Convert assembly non-generic methods", "args": { "durationMS": 12.7546, "detail": "UnityEngine.AudioModule" } },
{ "pid": 1, "tid": 1, "ts": 6031334.4, "dur": 91922.4, "ph": "X", "name": "Convert assembly non-generic methods", "args": { "durationMS": 91.9224, "detail": "UnityEngine.IMGUIModule" } },
{ "pid": 1, "tid": 1, "ts": 6123258.4, "dur": 638.8, "ph": "X", "name": "Convert assembly non-generic methods", "args": { "durationMS": 0.6388, "detail": "UnityEngine.SpriteShapeModule" } },
{ "pid": 1, "tid": 1, "ts": 6123898.4, "dur": 11062.4, "ph": "X", "name": "Convert assembly non-generic methods", "args": { "durationMS": 11.0624, "detail": "UnityEngine.TilemapModule" } },
{ "pid": 1, "tid": 1, "ts": 6134962.4, "dur": 27409.5, "ph": "X", "name": "Convert assembly non-generic methods", "args": { "durationMS": 27.4095, "detail": "UnityEngine.UIModule" } },
{ "pid": 1, "tid": 1, "ts": 6162374, "dur": 27337.3, "ph": "X", "name": "Convert assembly non-generic methods", "args": { "durationMS": 27.3373, "detail": "UnityEngine.UnityWebRequestModule" } },
{ "pid": 1, "tid": 1, "ts": 6189713.6, "dur": 37617, "ph": "X", "name": "Convert assembly non-generic methods", "args": { "durationMS": 37.617, "detail": "UnityEngine.XRModule" } },
{ "pid": 1, "tid": 1, "ts": 6227332, "dur": 1986.2, "ph": "X", "name": "Convert assembly non-generic methods", "args": { "durationMS": 1.9862, "detail": "UnityEngine.AIModule" } },
{ "pid": 1, "tid": 1, "ts": 6229319.6, "dur": 69656.8, "ph": "X", "name": "Convert assembly non-generic methods", "args": { "durationMS": 69.6568, "detail": "UnityEngine.AndroidJNIModule" } },
{ "pid": 1, "tid": 1, "ts": 6298978, "dur": 1782.7, "ph": "X", "name": "Convert assembly non-generic methods", "args": { "durationMS": 1.7827, "detail": "UnityEngine.DirectorModule" } },
{ "pid": 1, "tid": 1, "ts": 6300762, "dur": 48168.7, "ph": "X", "name": "Convert assembly non-generic methods", "args": { "durationMS": 48.1687, "detail": "UnityEngine.GameCenterModule" } },
{ "pid": 1, "tid": 1, "ts": 6348932.4, "dur": 5867.3, "ph": "X", "name": "Convert assembly non-generic methods", "args": { "durationMS": 5.8673, "detail": "UnityEngine.InputModule" } },
{ "pid": 1, "tid": 1, "ts": 6354801.6, "dur": 11837.5, "ph": "X", "name": "Convert assembly non-generic methods", "args": { "durationMS": 11.8375, "detail": "UnityEngine.ParticleSystemModule" } },
{ "pid": 1, "tid": 1, "ts": 6366640.8, "dur": 27788.2, "ph": "X", "name": "Convert assembly non-generic methods", "args": { "durationMS": 27.7882, "detail": "UnityEngine.TerrainModule" } },
{ "pid": 1, "tid": 1, "ts": 6394431.2, "dur": 37861.4, "ph": "X", "name": "Convert assembly non-generic methods", "args": { "durationMS": 37.8614, "detail": "UnityEngine.TextCoreModule" } },
{ "pid": 1, "tid": 1, "ts": 6432294.4, "dur": 945804.9, "ph": "X", "name": "Convert assembly non-generic methods", "args": { "durationMS": 945.8049, "detail": "UnityEngine.UI" } },
{ "pid": 1, "tid": 1, "ts": 7378100.8, "dur": 9189.9, "ph": "X", "name": "Convert assembly non-generic methods", "args": { "durationMS": 9.1899, "detail": "UnityEngine.UIElementsNativeModule" } },
{ "pid": 1, "tid": 1, "ts": 7387292.8, "dur": 6741.5, "ph": "X", "name": "Convert assembly non-generic methods", "args": { "durationMS": 6.7415, "detail": "UnityEngine.UnityAnalyticsModule" } },
{ "pid": 1, "tid": 1, "ts": 7394035.2, "dur": 3249.4, "ph": "X", "name": "Convert assembly non-generic methods", "args": { "durationMS": 3.2494, "detail": "UnityEngine.UnityWebRequestAssetBundleModule" } },
{ "pid": 1, "tid": 1, "ts": 7397286.4, "dur": 6177.4, "ph": "X", "name": "Convert assembly non-generic methods", "args": { "durationMS": 6.1774, "detail": "UnityEngine.VFXModule" } },
{ "pid": 1, "tid": 1, "ts": 7403465.6, "dur": 1234.2, "ph": "X", "name": "Convert assembly non-generic methods", "args": { "durationMS": 1.2342, "detail": "UnityEngine.VRModule" } },
{ "pid": 1, "tid": 1, "ts": 7404700.8, "dur": 7121.9, "ph": "X", "name": "Convert assembly non-generic methods", "args": { "durationMS": 7.1219, "detail": "UnityEngine.VideoModule" } },
{ "pid": 1, "tid": 1, "ts": 7411824, "dur": 1614770.8, "ph": "X", "name": "Convert assembly non-generic methods", "args": { "durationMS": 1614.7708, "detail": "Unity.TextMeshPro" } },
{ "pid": 1, "tid": 1, "ts": 9026596.8, "dur": 486.2, "ph": "X", "name": "Convert assembly non-generic methods", "args": { "durationMS": 0.4862, "detail": "UnityEngine" } },
{ "pid": 1, "tid": 1, "ts": 9027084.8, "dur": 149102.5, "ph": "X", "name": "Convert assembly non-generic methods", "args": { "durationMS": 149.1025, "detail": "Assembly-CSharp" } },
{ "pid": 1, "tid": 1, "ts": 9176311.2, "dur": 3435525.2, "ph": "X", "name": "WriteGenerics", "args": { "durationMS": 3435.5252, "detail": "" } },
{ "pid": 1, "tid": 1, "ts": 9177510.4, "dur": 798121.8, "ph": "X", "name": "GenericInstanceMethods", "args": { "durationMS": 798.1218, "detail": "" } },
{ "pid": 1, "tid": 1, "ts": 9975640, "dur": 2415317.6, "ph": "X", "name": "GenericInstanceTypes", "args": { "durationMS": 2415.3176, "detail": "" } },
{ "pid": 1, "tid": 1, "ts": 12391077.6, "dur": 220732.3, "ph": "X", "name": "GenericComDefinitions", "args": { "durationMS": 220.7323, "detail": "" } },
{ "pid": 1, "tid": 1, "ts": 12612116.8, "dur": 610.2, "ph": "X", "name": "Executable Processing", "args": { "durationMS": 0.6102, "detail": "" } },
{ "pid": 1, "tid": 1, "ts": 12614260, "dur": 229893.8, "ph": "X", "name": "MetadataCollector", "args": { "durationMS": 229.8938, "detail": "" } },
{ "pid": 1, "tid": 1, "ts": 12615217.6, "dur": 7512.1, "ph": "X", "name": "UpdateEmptyTokens", "args": { "durationMS": 7.5121, "detail": "" } },
{ "pid": 1, "tid": 1, "ts": 12623196, "dur": 9704.7, "ph": "X", "name": "ValidateTokens", "args": { "durationMS": 9.7047, "detail": "" } },
{ "pid": 1, "tid": 1, "ts": 12844556, "dur": 1535, "ph": "X", "name": "Write COM Callable Wrappers", "args": { "durationMS": 1.535, "detail": "" } },
{ "pid": 1, "tid": 1, "ts": 12846164, "dur": 422.7, "ph": "X", "name": "Write Windows Runtime Factories", "args": { "durationMS": 0.4227, "detail": "" } },
{ "pid": 1, "tid": 1, "ts": 12846841.6, "dur": 2348350.4, "ph": "X", "name": "Metadata", "args": { "durationMS": 2348.3504, "detail": "Global" } },
{ "pid": 1, "tid": 1, "ts": 12890901.6, "dur": 873664.3, "ph": "X", "name": "Il2CppAttributes.cpp", "args": { "durationMS": 873.6643, "detail": "" } },
{ "pid": 1, "tid": 1, "ts": 13893148.8, "dur": 13738.1, "ph": "X", "name": "UnresolvedVirtualCallStubs.cpp", "args": { "durationMS": 13.7381, "detail": "" } },
{ "pid": 1, "tid": 1, "ts": 13908528, "dur": 349871.9, "ph": "X", "name": "WriteCodeRegistration", "args": { "durationMS": 349.8719, "detail": "" } },
{ "pid": 1, "tid": 1, "ts": 13908558.4, "dur": 80913.5, "ph": "X", "name": "mscorlib_CodeGen.c", "args": { "durationMS": 80.9135, "detail": "" } },
{ "pid": 1, "tid": 1, "ts": 13978881.6, "dur": 3065.9, "ph": "X", "name": "GenericContextCollector", "args": { "durationMS": 3.0659, "detail": "Collect" } },
{ "pid": 1, "tid": 1, "ts": 13989488, "dur": 585.5, "ph": "X", "name": "System.Configuration_CodeGen.c", "args": { "durationMS": 0.5855, "detail": "" } },
{ "pid": 1, "tid": 1, "ts": 13990083.2, "dur": 509.1, "ph": "X", "name": "Mono.Security_CodeGen.c", "args": { "durationMS": 0.5091, "detail": "" } },
{ "pid": 1, "tid": 1, "ts": 13990601.6, "dur": 566.3, "ph": "X", "name": "System.Xml_CodeGen.c", "args": { "durationMS": 0.5663, "detail": "" } },
{ "pid": 1, "tid": 1, "ts": 13991177.6, "dur": 8100.2, "ph": "X", "name": "System_CodeGen.c", "args": { "durationMS": 8.1002, "detail": "" } },
{ "pid": 1, "tid": 1, "ts": 13999288, "dur": 1208.9, "ph": "X", "name": "System.Core_CodeGen.c", "args": { "durationMS": 1.2089, "detail": "" } },
{ "pid": 1, "tid": 1, "ts": 14000507.2, "dur": 880.4, "ph": "X", "name": "UnityEngine.SharedInternalsModule_CodeGen.c", "args": { "durationMS": 0.8804, "detail": "" } },
{ "pid": 1, "tid": 1, "ts": 14001396.8, "dur": 13873.5, "ph": "X", "name": "UnityEngine.CoreModule_CodeGen.c", "args": { "durationMS": 13.8735, "detail": "" } },
{ "pid": 1, "tid": 1, "ts": 14013516.8, "dur": 336.1, "ph": "X", "name": "GenericContextCollector", "args": { "durationMS": 0.3361, "detail": "Collect" } },
{ "pid": 1, "tid": 1, "ts": 14015283.2, "dur": 343.5, "ph": "X", "name": "UnityEngine.GridModule_CodeGen.c", "args": { "durationMS": 0.3435, "detail": "" } },
{ "pid": 1, "tid": 1, "ts": 14015636.8, "dur": 715.9, "ph": "X", "name": "UnityEngine.InputLegacyModule_CodeGen.c", "args": { "durationMS": 0.7159, "detail": "" } },
{ "pid": 1, "tid": 1, "ts": 14016361.6, "dur": 1155.7, "ph": "X", "name": "UnityEngine.Physics2DModule_CodeGen.c", "args": { "durationMS": 1.1557, "detail": "" } },
{ "pid": 1, "tid": 1, "ts": 14017526.4, "dur": 911.4, "ph": "X", "name": "UnityEngine.PhysicsModule_CodeGen.c", "args": { "durationMS": 0.9114, "detail": "" } },
{ "pid": 1, "tid": 1, "ts": 14018446.4, "dur": 518, "ph": "X", "name": "UnityEngine.SubsystemsModule_CodeGen.c", "args": { "durationMS": 0.518, "detail": "" } },
{ "pid": 1, "tid": 1, "ts": 14018974.4, "dur": 802.1, "ph": "X", "name": "UnityEngine.TextRenderingModule_CodeGen.c", "args": { "durationMS": 0.8021, "detail": "" } },
{ "pid": 1, "tid": 1, "ts": 14019785.6, "dur": 982.9, "ph": "X", "name": "UnityEngine.AnimationModule_CodeGen.c", "args": { "durationMS": 0.9829, "detail": "" } },
{ "pid": 1, "tid": 1, "ts": 14020777.6, "dur": 351.7, "ph": "X", "name": "UnityEngine.AssetBundleModule_CodeGen.c", "args": { "durationMS": 0.3517, "detail": "" } },
{ "pid": 1, "tid": 1, "ts": 14021139.2, "dur": 709.5, "ph": "X", "name": "UnityEngine.AudioModule_CodeGen.c", "args": { "durationMS": 0.7095, "detail": "" } },
{ "pid": 1, "tid": 1, "ts": 14021857.6, "dur": 2384.1, "ph": "X", "name": "UnityEngine.IMGUIModule_CodeGen.c", "args": { "durationMS": 2.3841, "detail": "" } },
{ "pid": 1, "tid": 1, "ts": 14024545.6, "dur": 631.6, "ph": "X", "name": "UnityEngine.TilemapModule_CodeGen.c", "args": { "durationMS": 0.6316, "detail": "" } },
{ "pid": 1, "tid": 1, "ts": 14025185.6, "dur": 1141.5, "ph": "X", "name": "UnityEngine.UIModule_CodeGen.c", "args": { "durationMS": 1.1415, "detail": "" } },
{ "pid": 1, "tid": 1, "ts": 14026337.6, "dur": 857.3, "ph": "X", "name": "UnityEngine.UnityWebRequestModule_CodeGen.c", "args": { "durationMS": 0.8573, "detail": "" } },
{ "pid": 1, "tid": 1, "ts": 14027203.2, "dur": 777.5, "ph": "X", "name": "UnityEngine.XRModule_CodeGen.c", "args": { "durationMS": 0.7775, "detail": "" } },
{ "pid": 1, "tid": 1, "ts": 14027990.4, "dur": 340.2, "ph": "X", "name": "UnityEngine.AIModule_CodeGen.c", "args": { "durationMS": 0.3402, "detail": "" } },
{ "pid": 1, "tid": 1, "ts": 14028339.2, "dur": 1780.7, "ph": "X", "name": "UnityEngine.AndroidJNIModule_CodeGen.c", "args": { "durationMS": 1.7807, "detail": "" } },
{ "pid": 1, "tid": 1, "ts": 14030454.4, "dur": 1603.7, "ph": "X", "name": "UnityEngine.GameCenterModule_CodeGen.c", "args": { "durationMS": 1.6037, "detail": "" } },
{ "pid": 1, "tid": 1, "ts": 14032067.2, "dur": 405.6, "ph": "X", "name": "UnityEngine.InputModule_CodeGen.c", "args": { "durationMS": 0.4056, "detail": "" } },
{ "pid": 1, "tid": 1, "ts": 14032481.6, "dur": 521.7, "ph": "X", "name": "UnityEngine.ParticleSystemModule_CodeGen.c", "args": { "durationMS": 0.5217, "detail": "" } },
{ "pid": 1, "tid": 1, "ts": 14033012.8, "dur": 779.1, "ph": "X", "name": "UnityEngine.TerrainModule_CodeGen.c", "args": { "durationMS": 0.7791, "detail": "" } },
{ "pid": 1, "tid": 1, "ts": 14033801.6, "dur": 1195.2, "ph": "X", "name": "UnityEngine.TextCoreModule_CodeGen.c", "args": { "durationMS": 1.1952, "detail": "" } },
{ "pid": 1, "tid": 1, "ts": 14035004.8, "dur": 13779.6, "ph": "X", "name": "UnityEngine.UI_CodeGen.c", "args": { "durationMS": 13.7796, "detail": "" } },
{ "pid": 1, "tid": 1, "ts": 14048796.8, "dur": 544.5, "ph": "X", "name": "UnityEngine.UIElementsNativeModule_CodeGen.c", "args": { "durationMS": 0.5445, "detail": "" } },
{ "pid": 1, "tid": 1, "ts": 14049350.4, "dur": 554.2, "ph": "X", "name": "UnityEngine.UnityAnalyticsModule_CodeGen.c", "args": { "durationMS": 0.5542, "detail": "" } },
{ "pid": 1, "tid": 1, "ts": 14049913.6, "dur": 362.4, "ph": "X", "name": "UnityEngine.UnityWebRequestAssetBundleModule_CodeGen.c", "args": { "durationMS": 0.3624, "detail": "" } },
{ "pid": 1, "tid": 1, "ts": 14050283.2, "dur": 417.4, "ph": "X", "name": "UnityEngine.VFXModule_CodeGen.c", "args": { "durationMS": 0.4174, "detail": "" } },
{ "pid": 1, "tid": 1, "ts": 14051014.4, "dur": 1042.5, "ph": "X", "name": "UnityEngine.VideoModule_CodeGen.c", "args": { "durationMS": 1.0425, "detail": "" } },
{ "pid": 1, "tid": 1, "ts": 14052065.6, "dur": 17855.6, "ph": "X", "name": "Unity.TextMeshPro_CodeGen.c", "args": { "durationMS": 17.8556, "detail": "" } },
{ "pid": 1, "tid": 1, "ts": 14070228.8, "dur": 2926.6, "ph": "X", "name": "Assembly-CSharp_CodeGen.c", "args": { "durationMS": 2.9266, "detail": "" } },
{ "pid": 1, "tid": 1, "ts": 14073756.8, "dur": 635.8, "ph": "X", "name": "Il2CppReversePInvokeWrapperTable.cpp", "args": { "durationMS": 0.6358, "detail": "" } },
{ "pid": 1, "tid": 1, "ts": 14074560, "dur": 92517.3, "ph": "X", "name": "Il2CppGenericMethodPointerTable.cpp", "args": { "durationMS": 92.5173, "detail": "" } },
{ "pid": 1, "tid": 1, "ts": 14167225.6, "dur": 71787.9, "ph": "X", "name": "Il2CppInvokerTable.cpp", "args": { "durationMS": 71.7879, "detail": "" } },
{ "pid": 1, "tid": 1, "ts": 14239545.6, "dur": 16321.9, "ph": "X", "name": "Il2CppInteropDataTable.cpp", "args": { "durationMS": 16.3219, "detail": "" } },
{ "pid": 1, "tid": 1, "ts": 14257512, "dur": 886.4, "ph": "X", "name": "Il2CppCodeRegistration.cpp", "args": { "durationMS": 0.8864, "detail": "" } },
{ "pid": 1, "tid": 1, "ts": 14258403.2, "dur": 936787.2, "ph": "X", "name": "WriteMetadata", "args": { "durationMS": 936.7872, "detail": "" } },
{ "pid": 1, "tid": 1, "ts": 14263793.6, "dur": 179767.6, "ph": "X", "name": "Il2CppMetadataUsage.c", "args": { "durationMS": 179.7676, "detail": "" } },
{ "pid": 1, "tid": 1, "ts": 14338022.4, "dur": 3147.1, "ph": "X", "name": "Metadata", "args": { "durationMS": 3.1471, "detail": "Collect string literals" } },
{ "pid": 1, "tid": 1, "ts": 14454814.4, "dur": 20917.6, "ph": "X", "name": "Il2CppGenericClassTable.c", "args": { "durationMS": 20.9176, "detail": "" } },
{ "pid": 1, "tid": 1, "ts": 14475745.6, "dur": 23589.1, "ph": "X", "name": "Il2CppGenericInstDefinitions.c", "args": { "durationMS": 23.5891, "detail": "" } },
{ "pid": 1, "tid": 1, "ts": 14499350.4, "dur": 252746.5, "ph": "X", "name": "Il2CppGenericMethodTable.c", "args": { "durationMS": 252.7465, "detail": "" } },
{ "pid": 1, "tid": 1, "ts": 14752110.4, "dur": 78000.7, "ph": "X", "name": "Il2CppTypeDefinitions.c", "args": { "durationMS": 78.0007, "detail": "" } },
{ "pid": 1, "tid": 1, "ts": 14830129.6, "dur": 47267.2, "ph": "X", "name": "Il2CppGenericMethodDefinitions.c", "args": { "durationMS": 47.2672, "detail": "" } },
{ "pid": 1, "tid": 1, "ts": 14877403.2, "dur": 135431.2, "ph": "X", "name": "CompilerCalculateTypeValues", "args": { "durationMS": 135.4312, "detail": "" } },
{ "pid": 1, "tid": 1, "ts": 15012852.8, "dur": 2255.1, "ph": "X", "name": "Il2CppMetadataRegistration.c", "args": { "durationMS": 2.2551, "detail": "" } },
{ "pid": 1, "tid": 1, "ts": 15015440, "dur": 6480.4, "ph": "X", "name": "StringLiteralWriter", "args": { "durationMS": 6.4804, "detail": "" } },
{ "pid": 1, "tid": 1, "ts": 15022020.8, "dur": 896.3, "ph": "X", "name": "Metadata Strings", "args": { "durationMS": 0.8963, "detail": "" } },
{ "pid": 1, "tid": 1, "ts": 15022924.8, "dur": 4026.3, "ph": "X", "name": "Events", "args": { "durationMS": 4.0263, "detail": "" } },
{ "pid": 1, "tid": 1, "ts": 15026953.6, "dur": 7218.5, "ph": "X", "name": "Properties", "args": { "durationMS": 7.2185, "detail": "" } },
{ "pid": 1, "tid": 1, "ts": 15034179.2, "dur": 51767.1, "ph": "X", "name": "Methods", "args": { "durationMS": 51.7671, "detail": "" } },
{ "pid": 1, "tid": 1, "ts": 15085955.2, "dur": 3553.8, "ph": "X", "name": "Parameter Default Values", "args": { "durationMS": 3.5538, "detail": "" } },
{ "pid": 1, "tid": 1, "ts": 15089513.6, "dur": 4123.3, "ph": "X", "name": "Field Default Values", "args": { "durationMS": 4.1233, "detail": "" } },
{ "pid": 1, "tid": 1, "ts": 15093876.8, "dur": 448.3, "ph": "X", "name": "Field Marshaled Sizes", "args": { "durationMS": 0.4483, "detail": "" } },
{ "pid": 1, "tid": 1, "ts": 15094329.6, "dur": 12956.5, "ph": "X", "name": "Parameters", "args": { "durationMS": 12.9565, "detail": "" } },
{ "pid": 1, "tid": 1, "ts": 15107296, "dur": 9646.5, "ph": "X", "name": "Fields", "args": { "durationMS": 9.6465, "detail": "" } },
{ "pid": 1, "tid": 1, "ts": 15116950.4, "dur": 3722.4, "ph": "X", "name": "Generic Parameters", "args": { "durationMS": 3.7224, "detail": "" } },
{ "pid": 1, "tid": 1, "ts": 15120678.4, "dur": 762.9, "ph": "X", "name": "Generic Parameter Constraints", "args": { "durationMS": 0.7629, "detail": "" } },
{ "pid": 1, "tid": 1, "ts": 15121446.4, "dur": 3324.7, "ph": "X", "name": "Generic Containers", "args": { "durationMS": 3.3247, "detail": "" } },
{ "pid": 1, "tid": 1, "ts": 15125144, "dur": 1784.9, "ph": "X", "name": "VTables", "args": { "durationMS": 1.7849, "detail": "" } },
{ "pid": 1, "tid": 1, "ts": 15126934.4, "dur": 1128.6, "ph": "X", "name": "Interface Offsets", "args": { "durationMS": 1.1286, "detail": "" } },
{ "pid": 1, "tid": 1, "ts": 15128067.2, "dur": 47056.2, "ph": "X", "name": "Type Definitions", "args": { "durationMS": 47.0562, "detail": "" } },
{ "pid": 1, "tid": 1, "ts": 15175136, "dur": 4579.9, "ph": "X", "name": "Images", "args": { "durationMS": 4.5799, "detail": "" } },
{ "pid": 1, "tid": 1, "ts": 15179720, "dur": 3046.8, "ph": "X", "name": "Assemblies", "args": { "durationMS": 3.0468, "detail": "" } },
{ "pid": 1, "tid": 1, "ts": 15182769.6, "dur": 741.5, "ph": "X", "name": "Metadata Usage Lists", "args": { "durationMS": 0.7415, "detail": "" } },
{ "pid": 1, "tid": 1, "ts": 15183515.2, "dur": 3414.1, "ph": "X", "name": "Metadata Usage Pairs", "args": { "durationMS": 3.4141, "detail": "" } },
{ "pid": 1, "tid": 1, "ts": 15187051.2, "dur": 418.6, "ph": "X", "name": "Referenced Assemblies", "args": { "durationMS": 0.4186, "detail": "" } },
{ "pid": 1, "tid": 1, "ts": 15187473.6, "dur": 892.3, "ph": "X", "name": "Attribute Types Ranges", "args": { "durationMS": 0.8923, "detail": "" } },
{ "pid": 1, "tid": 1, "ts": 15188369.6, "dur": 512, "ph": "X", "name": "Attribute Types", "args": { "durationMS": 0.512, "detail": "" } },
{ "pid": 1, "tid": 1, "ts": 15189019.2, "dur": 515.3, "ph": "X", "name": "Unresolved Virtual Call Parameter Ranges", "args": { "durationMS": 0.5153, "detail": "" } },
{ "pid": 1, "tid": 1, "ts": 15189702.4, "dur": 3616.3, "ph": "X", "name": "Exported Types", "args": { "durationMS": 3.6163, "detail": "" } },
{ "pid": 1, "tid": 1, "ts": 15195336, "dur": 570.5, "ph": "X", "name": "CompletionPhase", "args": { "durationMS": 0.5705, "detail": "" } }
],
"meta_datetime": "11/15/2020 09:01:31",
"meta_command_line": "/Applications/Unity/Hub/Editor/2020.1.13f1/Unity.app/Contents/il2cpp/build/deploy/net471/il2cpp.exe --convert-to-cpp --emit-null-checks --enable-array-bounds-check --dotnetprofile=unityaot --incremental-g-c-time-slice=3 --avoid-dynamic-library-copy --profiler-report --map-file-parser=/Applications/Unity/Hub/Editor/2020.1.13f1/Unity.app/Contents/Tools/MapFileParser/MapFileParser --directory=/Users/d/dev/src/github.com/davidbyttow/ImpossibleGames/Temp/StagingArea/Data/Managed --generatedcppdir=/Users/d/dev/src/github.com/davidbyttow/ImpossibleGames/Temp/il2cppOutput/il2cppOutput",
"meta_command_line_args": "/Applications/Unity/Hub/Editor/2020.1.13f1/Unity.app/Contents/il2cpp/build/deploy/net471/il2cpp.exe --convert-to-cpp --emit-null-checks --enable-array-bounds-check --dotnetprofile=unityaot --incremental-g-c-time-slice=3 --avoid-dynamic-library-copy --profiler-report --map-file-parser=/Applications/Unity/Hub/Editor/2020.1.13f1/Unity.app/Contents/Tools/MapFileParser/MapFileParser --directory=/Users/d/dev/src/github.com/davidbyttow/ImpossibleGames/Temp/StagingArea/Data/Managed --generatedcppdir=/Users/d/dev/src/github.com/davidbyttow/ImpossibleGames/Temp/il2cppOutput/il2cppOutput",
"meta_user_name": "d",
"meta_os_version": "Unix 20.1.0.0",
"meta_cpu_count": "16"}
